[
  {
    "Hisse_Kodu": "YKBNK",
    "Hisse_Adi": "YAPI VE KREDİ BANKASI A.Ş.",
    "Ay": "2024-03",
    "Alis_Nominal_TL": 1629091053.225,
    "Alis_Tutar_TL": 39722889990.393,
    "Alis_Tutar_USD": 1240141459.24103,
    "Satis_Nominal_TL": 1464354887.225,
    "Satis_Tutar_TL": 35489338867.7495,
    "Satis_Tutar_USD": 1109289021.37963,
    "Net_Nominal_TL": 164736166.0,
    "Net_Tutar_TL": 4233551122.6435013,
    "Net_Tutar_USD": 130852437.86139989
  },
  {
    "Hisse_Kodu": "AKFYE",
    "Hisse_Adi": "AKFEN YENİLENEBİLİR ENERJİ A.Ş.",
    "Ay": "2024-03",
    "Alis_Nominal_TL": 163672165.0,
    "Alis_Tutar_TL": 4680209936.88,
    "Alis_Tutar_USD": 146614540.764713,
    "Satis_Nominal_TL": 125032923.0,
    "Satis_Tutar_TL": 3490842096.7,
    "Satis_Tutar_USD": 109270087.621185,
    "Net_Nominal_TL": 38639242.0,
    "Net_Tutar_TL": 1189367840.1800003,
    "Net_Tutar_USD": 37344453.143527985
  },
  {
    "Hisse_Kodu": "MIATK",
    "Hisse_Adi": "MİA TEKNOLOJİ A.Ş.",
    "Ay": "2024-03",
    "Alis_Nominal_TL": 237723903.5,
    "Alis_Tutar_TL": 17069028278.725,
    "Alis_Tutar_USD": 535664368.062581,
    "Satis_Nominal_TL": 212827586.5,
    "Satis_Tutar_TL": 15470322183.575,
    "Satis_Tutar_USD": 486214639.410649,
    "Net_Nominal_TL": 24896317.0,
    "Net_Tutar_TL": 1598706095.1499996,
    "Net_Tutar_USD": 49449728.651932
  },
  {
    "Hisse_Kodu": "ZOREN",
    "Hisse_Adi": "ZORLU ENERJİ ELEKTRİK ÜRETİM A.Ş.",
    "Ay": "2024-03",
    "Alis_Nominal_TL": 722123239.0,
    "Alis_Tutar_TL": 4021526588.74,
    "Alis_Tutar_USD": 125518856.31993,
    "Satis_Nominal_TL": 697630338.0,
    "Satis_Tutar_TL": 3888133888.28,
    "Satis_Tutar_USD": 121381141.325356,
    "Net_Nominal_TL": 24492901.0,
    "Net_Tutar_TL": 133392700.45999956,
    "Net_Tutar_USD": 4137714.9945739955
  },
  {
    "Hisse_Kodu": "HALKB",
    "Hisse_Adi": "TÜRKİYE HALK BANKASI A.Ş.",
    "Ay": "2024-03",
    "Alis_Nominal_TL": 317421069.0,
    "Alis_Tutar_TL": 4326462587.22,
    "Alis_Tutar_USD": 135420490.641824,
    "Satis_Nominal_TL": 298866783.0,
    "Satis_Tutar_TL": 4076870486.12,
    "Satis_Tutar_USD": 127612869.191183,
    "Net_Nominal_TL": 18554286.0,
    "Net_Tutar_TL": 249592101.10000038,
    "Net_Tutar_USD": 7807621.450641006
  },
  {
    "Hisse_Kodu": "PSGYO",
    "Hisse_Adi": "PASİFİK GAYRİMENKUL YATIRIM ORTAKLIĞI A.Ş.",
    "Ay": "2024-03",
    "Alis_Nominal_TL": 165030380.0,
    "Alis_Tutar_TL": 1170863272.88,
    "Alis_Tutar_USD": 36714599.2052413,
    "Satis_Nominal_TL": 147851271.0,
    "Satis_Tutar_TL": 1068211824.9,
    "Satis_Tutar_USD": 33525487.2235918,
    "Net_Nominal_TL": 17179109.0,
    "Net_Tutar_TL": 102651447.98000014,
    "Net_Tutar_USD": 3189111.9816494994
  },
  {
    "Hisse_Kodu": "REEDR",
    "Hisse_Adi": "REEDER TEKNOLOJİ SANAYİ VE TİCARET A.Ş.",
    "Ay": "2024-03",
    "Alis_Nominal_TL": 290430475.0,
    "Alis_Tutar_TL": 18054841764.5,
    "Alis_Tutar_USD": 567988216.331349,
    "Satis_Nominal_TL": 276134713.0,
    "Satis_Tutar_TL": 17263817830.18,
    "Satis_Tutar_USD": 543256174.497124,
    "Net_Nominal_TL": 14295762.0,
    "Net_Tutar_TL": 791023934.3199997,
    "Net_Tutar_USD": 24732041.83422506
  },
  {
    "Hisse_Kodu": "KCHOL",
    "Hisse_Adi": "KOÇ HOLDİNG A.Ş.",
    "Ay": "2024-03",
    "Alis_Nominal_TL": 167534002.5,
    "Alis_Tutar_TL": 30814158161.65,
    "Alis_Tutar_USD": 962853968.34898,
    "Satis_Nominal_TL": 153330112.0,
    "Satis_Tutar_TL": 28094668201.3,
    "Satis_Tutar_USD": 878360716.637358,
    "Net_Nominal_TL": 14203890.5,
    "Net_Tutar_TL": 2719489960.3500023,
    "Net_Tutar_USD": 84493251.711622
  },
  {
    "Hisse_Kodu": "KATMR",
    "Hisse_Adi": "KATMERCİLER ARAÇ ÜSTÜ EKİPMAN SANAYİ A.Ş.",
    "Ay": "2024-03",
    "Alis_Nominal_TL": 261477175.0,
    "Alis_Tutar_TL": 611973457.14,
    "Alis_Tutar_USD": 19189562.5531475,
    "Satis_Nominal_TL": 247845666.0,
    "Satis_Tutar_TL": 579226720.5,
    "Satis_Tutar_USD": 18151513.9723666,
    "Net_Nominal_TL": 13631509.0,
    "Net_Tutar_TL": 32746736.639999986,
    "Net_Tutar_USD": 1038048.5807808973
  },
  {
    "Hisse_Kodu": "SKBNK",
    "Hisse_Adi": "ŞEKERBANK T.A.Ş.",
    "Ay": "2024-03",
    "Alis_Nominal_TL": 297824206.0,
    "Alis_Tutar_TL": 1319715209.67,
    "Alis_Tutar_USD": 41321798.3996075,
    "Satis_Nominal_TL": 285401569.0,
    "Satis_Tutar_TL": 1266849575.79,
    "Satis_Tutar_USD": 39665803.0294061,
    "Net_Nominal_TL": 12422637.0,
    "Net_Tutar_TL": 52865633.880000114,
    "Net_Tutar_USD": 1655995.3702014014
  }
]