[
  {
    "Hisse_Kodu": "SASA",
    "Hisse_Adi": "SASA POLYESTER  SANAYİ A.Ş.",
    "Ay": "2026-02",
    "Alis_Nominal_TL": 21680090822.0,
    "Alis_Tutar_TL": 55421245478.04,
    "Alis_Tutar_USD": 1271391947.93105,
    "Satis_Nominal_TL": 22072942350.0,
    "Satis_Tutar_TL": 56488599264.19,
    "Satis_Tutar_USD": 1295952483.20319,
    "Net_Nominal_TL": -392851528.0,
    "Net_Tutar_TL": -1067353786.1500015,
    "Net_Tutar_USD": -24560535.272140026
  },
  {
    "Hisse_Kodu": "PAHOL",
    "Hisse_Adi": "PASİFİK HOLDİNG A.Ş.",
    "Ay": "2026-02",
    "Alis_Nominal_TL": 2272302415.0,
    "Alis_Tutar_TL": 3865575616.57,
    "Alis_Tutar_USD": 88773491.3730058,
    "Satis_Nominal_TL": 2480824344.0,
    "Satis_Tutar_TL": 4234020754.93,
    "Satis_Tutar_USD": 97253811.0681264,
    "Net_Nominal_TL": -208521929.0,
    "Net_Tutar_TL": -368445138.35999966,
    "Net_Tutar_USD": -8480319.695120588
  },
  {
    "Hisse_Kodu": "HEKTS",
    "Hisse_Adi": "HEKTAŞ TİCARET T.A.Ş.",
    "Ay": "2026-02",
    "Alis_Nominal_TL": 2043457512.5,
    "Alis_Tutar_TL": 6781382245.775,
    "Alis_Tutar_USD": 155555495.603431,
    "Satis_Nominal_TL": 2157165285.5,
    "Satis_Tutar_TL": 7166055241.985,
    "Satis_Tutar_USD": 164368142.809821,
    "Net_Nominal_TL": -113707773.0,
    "Net_Tutar_TL": -384672996.21000004,
    "Net_Tutar_USD": -8812647.206390023
  },
  {
    "Hisse_Kodu": "QUAGR",
    "Hisse_Adi": "QUA GRANITE HAYAL YAPI VE ÜRÜNLERİ SANAYİ VE TİCARET A.Ş.",
    "Ay": "2026-02",
    "Alis_Nominal_TL": 1180029649.5,
    "Alis_Tutar_TL": 3552195757.12,
    "Alis_Tutar_USD": 81500421.5426026,
    "Satis_Nominal_TL": 1284273032.5,
    "Satis_Tutar_TL": 3915492595.875,
    "Satis_Tutar_USD": 89837060.2601535,
    "Net_Nominal_TL": -104243383.0,
    "Net_Tutar_TL": -363296838.7550001,
    "Net_Tutar_USD": -8336638.717550904
  },
  {
    "Hisse_Kodu": "GSRAY",
    "Hisse_Adi": "GALATASARAY SPORTİF SINAİ VE TİCARİ YATIRIMLAR A.Ş",
    "Ay": "2026-02",
    "Alis_Nominal_TL": 2777718894.5,
    "Alis_Tutar_TL": 3495769808.05,
    "Alis_Tutar_USD": 80139015.8634797,
    "Satis_Nominal_TL": 2869736074.0,
    "Satis_Tutar_TL": 3618727860.53,
    "Satis_Tutar_USD": 82935958.1101278,
    "Net_Nominal_TL": -92017179.5,
    "Net_Tutar_TL": -122958052.48000002,
    "Net_Tutar_USD": -2796942.246648103
  },
  {
    "Hisse_Kodu": "EKGYO",
    "Hisse_Adi": "EMLAK KONUT GAYRİMENKUL YATIRIM ORTAKLIĞI A.Ş.",
    "Ay": "2026-02",
    "Alis_Nominal_TL": 1465063595.0,
    "Alis_Tutar_TL": 36775515988.26,
    "Alis_Tutar_USD": 843815680.47137,
    "Satis_Nominal_TL": 1519069473.0,
    "Satis_Tutar_TL": 38128848810.82,
    "Satis_Tutar_USD": 874849645.862846,
    "Net_Nominal_TL": -54005878.0,
    "Net_Tutar_TL": -1353332822.5599976,
    "Net_Tutar_USD": -31033965.391476035
  },
  {
    "Hisse_Kodu": "OYAKC",
    "Hisse_Adi": "OYAK ÇİMENTO FABRİKALARI A.Ş.",
    "Ay": "2026-02",
    "Alis_Nominal_TL": 219365552.0,
    "Alis_Tutar_TL": 5777830007.88,
    "Alis_Tutar_USD": 132539093.954947,
    "Satis_Nominal_TL": 257300762.0,
    "Satis_Tutar_TL": 6808336774.68,
    "Satis_Tutar_USD": 156193946.928477,
    "Net_Nominal_TL": -37935210.0,
    "Net_Tutar_TL": -1030506766.8000002,
    "Net_Tutar_USD": -23654852.973529994
  },
  {
    "Hisse_Kodu": "TSKB",
    "Hisse_Adi": "TÜRKİYE SINAİ KALKINMA BANKASI A.Ş.",
    "Ay": "2026-02",
    "Alis_Nominal_TL": 415367053.0,
    "Alis_Tutar_TL": 5631786937.37,
    "Alis_Tutar_USD": 129215968.204683,
    "Satis_Nominal_TL": 451709187.0,
    "Satis_Tutar_TL": 6098202545.65,
    "Satis_Tutar_USD": 139936974.873854,
    "Net_Nominal_TL": -36342134.0,
    "Net_Tutar_TL": -466415608.27999973,
    "Net_Tutar_USD": -10721006.669171005
  },
  {
    "Hisse_Kodu": "TUPRS",
    "Hisse_Adi": "TÜPRAŞ TÜRKİYE PETROL RAFİNERİLERİ A.Ş.",
    "Ay": "2026-02",
    "Alis_Nominal_TL": 255957891.0,
    "Alis_Tutar_TL": 57235461101.3,
    "Alis_Tutar_USD": 1313331432.56339,
    "Satis_Nominal_TL": 291614670.0,
    "Satis_Tutar_TL": 65174574775.3,
    "Satis_Tutar_USD": 1495480408.21426,
    "Net_Nominal_TL": -35656779.0,
    "Net_Tutar_TL": -7939113674.0,
    "Net_Tutar_USD": -182148975.65087008
  },
  {
    "Hisse_Kodu": "GENIL",
    "Hisse_Adi": "GEN İLAÇ VE SAĞLIK ÜRÜNLERİ SANAYİ VE TİCARET A.Ş.",
    "Ay": "2026-02",
    "Alis_Nominal_TL": 172680060.0,
    "Alis_Tutar_TL": 1857292610.04,
    "Alis_Tutar_USD": 42597970.6770259,
    "Satis_Nominal_TL": 208050212.0,
    "Satis_Tutar_TL": 2289166099.715,
    "Satis_Tutar_USD": 52514611.7197519,
    "Net_Nominal_TL": -35370152.0,
    "Net_Tutar_TL": -431873489.6750002,
    "Net_Tutar_USD": -9916641.042726003
  }
]